collider_dashboard/__init__.py
collider_dashboard/__main__.py
collider_dashboard/assets/favicon.ico
collider_dashboard/assets/style.css
collider_dashboard/backend/__init__.py
collider_dashboard/backend/compute_globals.py
collider_dashboard/backend/fillingpatterns/__init__.py
collider_dashboard/backend/fillingpatterns/bbFunctions.py
collider_dashboard/backend/fillingpatterns/disclaimer.md
collider_dashboard/backend/fillingpatterns/dotdict.py
collider_dashboard/backend/fillingpatterns/filling_pattern.py
collider_dashboard/backend/fillingpatterns/mystyle.py
collider_dashboard/backend/plot.py
collider_dashboard/backend/resonance.py
collider_dashboard/callbacks.py
collider_dashboard/dashboard.py
collider_dashboard/data/25ns_2760b_2748_2492_2574_288bpi_13inj_800ns_bs200ns_converted.json
collider_dashboard/data/collider.json
collider_dashboard/layout/__init__.py
collider_dashboard/layout/configuration.py
collider_dashboard/layout/filling.py
collider_dashboard/layout/footprint.py
collider_dashboard/layout/header.py
collider_dashboard/layout/knob.py
collider_dashboard/layout/main.py
collider_dashboard/layout/optics.py
collider_dashboard/layout/sanity.py
collider_dashboard/layout/separation.py
collider_dashboard/layout/separation_3D.py
collider_dashboard/layout/survey.py
collider_dashboard/layout/tables.py
collider_dashboard/temp/.gitkeep
collider_dashboard-1.5.2.0.dist-info/LICENSE
collider_dashboard-1.5.2.0.dist-info/METADATA
collider_dashboard-1.5.2.0.dist-info/WHEEL
collider_dashboard-1.5.2.0.dist-info/RECORD
