Metadata-Version: 2.1
Name: collider-dashboard
Version: 1.5.2.0
Summary: A Dash application to visualize the observables and parameters of a collider built and configured with Xsuite.
Home-page: https://github.com/ColasDroin/simulation-dashboard
License: MIT
Author: Colas Droin
Author-email: colas.noe.droin@cern.ch
Requires-Python: >=3.10,<3.13
Classifier: License :: OSI Approved :: MIT License
Classifier: Programming Language :: Python :: 3
Classifier: Programming Language :: Python :: 3.10
Classifier: Programming Language :: Python :: 3.11
Classifier: Programming Language :: Python :: 3.12
Requires-Dist: argparse (>=1.4.0,<2.0.0)
Requires-Dist: collider-check (>=0.3.2,<0.4.0)
Requires-Dist: dash (>=2.18.2,<3.0.0)
Requires-Dist: dash-iconify (>=0.1.2,<0.2.0)
Requires-Dist: dash-mantine-components (>=0.12.1,<0.13.0)
Requires-Dist: numpy (>=2.1.2,<3.0.0)
Requires-Dist: pandas (>=2.2.3,<3.0.0)
Requires-Dist: seaborn (>=0.13.0,<0.14.0)
Requires-Dist: xsuite (>=0.19.2,<0.20.0)
Project-URL: Repository, https://github.com/ColasDroin/simulation-dashboard
